crossref_lmdb/__init__.py
crossref_lmdb/cli.py
crossref_lmdb/date.py
crossref_lmdb/db.py
crossref_lmdb/file.py
crossref_lmdb/filt.py
crossref_lmdb/items.py
crossref_lmdb/log.py
crossref_lmdb/main.py
crossref_lmdb/params.py
crossref_lmdb/py.typed
crossref_lmdb/web.py
crossref_lmdb-0.1.2.dist-info/METADATA
crossref_lmdb-0.1.2.dist-info/WHEEL
crossref_lmdb-0.1.2.dist-info/entry_points.txt
crossref_lmdb-0.1.2.dist-info/licenses/LICENSE
crossref_lmdb-0.1.2.dist-info/RECORD
