Metadata-Version: 2.4
Name: crossref-lmdb
Version: 0.1.2
Summary: A command-line application and Python library for accessing DOI metadata from a CrossRef public data export via a Lightning key:value (DOI:metadata) database.
Project-URL: Documentation, https://unimelbmdap.github.io/crossref-lmdb/
Project-URL: Repository, https://github.com/unimelbmdap/crossref-lmdb
Project-URL: Issues, https://github.com/unimelbmdap/crossref-lmdb/issues
Author-email: Damien Mannion <damien.mannion@unimelb.edu.au>
License-Expression: MIT
License-File: LICENSE
Classifier: Programming Language :: Python
Classifier: Programming Language :: Python :: 3.10
Classifier: Programming Language :: Python :: 3.11
Classifier: Programming Language :: Python :: 3.12
Requires-Python: >=3.10
Requires-Dist: alive-progress>=3.2.0
Requires-Dist: email-validator>=2.2.0
Requires-Dist: lmdb>=1.5.1
Requires-Dist: pysimdjson>=6.0.2
Requires-Dist: requests-ratelimiter>=0.7.0
Requires-Dist: requests>=2.32.3
Requires-Dist: retryhttp>=1.1.0
Requires-Dist: tenacity>=9.0.0
Provides-Extra: docs
Requires-Dist: enum-tools[sphinx]>=0.12.0; extra == 'docs'
Requires-Dist: furo>=2024.8.6; extra == 'docs'
Requires-Dist: sphinx-argparse-cli>=1.18.2; extra == 'docs'
Requires-Dist: sphinx-argparse>=0.5.2; extra == 'docs'
Requires-Dist: sphinx-autobuild>=2024.10.3; extra == 'docs'
Requires-Dist: sphinx-autodoc-typehints>=2.4.4; extra == 'docs'
Requires-Dist: sphinx-toolbox>=3.8.0; extra == 'docs'
Requires-Dist: sphinx>=8.0.2; extra == 'docs'
Provides-Extra: interactive
Requires-Dist: ipython>=8.27.0; extra == 'interactive'
